hemenson.py
hemenson_pypi-1.0.0.dist-info/METADATA
hemenson_pypi-1.0.0.dist-info/WHEEL
hemenson_pypi-1.0.0.dist-info/top_level.txt
hemenson_pypi-1.0.0.dist-info/RECORD
