Metadata-Version: 2.1
Name: hemenson-pypi
Version: 1.0.0
Summary: Brincando com distribuição python
Home-page: UNKNOWN
Author: Hemenson David silva
Author-email: UNKNOWN
License: UNKNOWN
Platform: UNKNOWN
